hello_world.py
helloworld_custom-0.0.2.dist-info/METADATA
helloworld_custom-0.0.2.dist-info/WHEEL
helloworld_custom-0.0.2.dist-info/top_level.txt
helloworld_custom-0.0.2.dist-info/RECORD
