Metadata-Version: 2.1
Name: helloworld-custom
Version: 0.0.2
Summary: hello world project
Home-page: UNKNOWN
Author: starting_out
Author-email: starting_out@xyz.com
License: UNKNOWN
Platform: UNKNOWN
